simple_bert_pytorch/__init__.py
simple_bert_pytorch/common.py
simple_bert_pytorch/modules.py
simple_bert_pytorch/tokenizer.py
simple_bert_pytorch/vocab-cased.json
simple_bert_pytorch/vocab-uncased.json
simple_bert_pytorch/models/__init__.py
simple_bert_pytorch/models/bert.py
simple_bert_pytorch/models/bge.py
simple_bert_pytorch/models/cross_encoder.py
tests/models/__init__.py
tests/models/test_bert.py
tests/models/test_bge.py
tests/models/test_cross_encoder.py
simple_bert_pytorch-0.2.0.dist-info/LICENSE
simple_bert_pytorch-0.2.0.dist-info/METADATA
simple_bert_pytorch-0.2.0.dist-info/WHEEL
simple_bert_pytorch-0.2.0.dist-info/top_level.txt
simple_bert_pytorch-0.2.0.dist-info/RECORD
