Metadata-Version: 2.1
Name: simple-bert-pytorch
Version: 0.2.0
Summary: simple-bert-pytorch
Author-email: Frank Odom <frank.odom.iii@gmail.com>
License: MIT
Classifier: Programming Language :: Python :: 3
Requires-Python: >=3.9
License-File: LICENSE
Requires-Dist: torch <3,>=2.0
Provides-Extra: test
Requires-Dist: transformers ==4.44.2 ; extra == 'test'
Requires-Dist: black ==24.8.0 ; extra == 'test'
Requires-Dist: mypy ==1.11.1 ; extra == 'test'
Requires-Dist: pre-commit ==3.8.0 ; extra == 'test'
Requires-Dist: pytest ==8.3.2 ; extra == 'test'
Requires-Dist: pytest-cov ==5.0.0 ; extra == 'test'
Requires-Dist: ruff ==0.6.2 ; extra == 'test'
